pigeon_js/__init__.py
pigeon_js/__main__.py
pigeon_js-1.0.0.dist-info/licenses/LICENSE
pigeon_js-1.0.0.dist-info/METADATA
pigeon_js-1.0.0.dist-info/WHEEL
pigeon_js-1.0.0.dist-info/entry_points.txt
pigeon_js-1.0.0.dist-info/top_level.txt
pigeon_js-1.0.0.dist-info/RECORD
