Metadata-Version: 2.4
Name: pigeon.js
Version: 1.0.0
Summary: A JavaScript Pigeon message converter.
Author-email: Cameron Devine <cameron.devine@alleninstitute.org>
Requires-Python: >=3.10
License-File: LICENSE
Requires-Dist: pigeon-client
Dynamic: license-file
